rtreelib/__init__.py
rtreelib/__version__.py
rtreelib/diagram.py
rtreelib/pg.py
rtreelib/rect.py
rtreelib/rtree.py
rtreelib/models/__init__.py
rtreelib/models/axis.py
rtreelib/models/dimension.py
rtreelib/models/entry_distribution.py
rtreelib/models/location.py
rtreelib/models/point.py
rtreelib/models/rect.py
rtreelib/models/rstar_cache.py
rtreelib/models/rstar_stat.py
rtreelib/sql/clear_rtree_tables.sql.template
rtreelib/sql/create_rtree_tables.sql.template
rtreelib/sql/drop_rtree_tables.sql.template
rtreelib/sql/insert_rtree.sql.template
rtreelib/sql/insert_rtree_entry.sql.template
rtreelib/sql/insert_rtree_node.sql.template
rtreelib/strategies/__init__.py
rtreelib/strategies/base.py
rtreelib/strategies/guttman.py
rtreelib/strategies/rstar.py
rtreelib/util/__init__.py
rtreelib/util/diagram.py
rtreelib/util/postgis.py
rtreelib-0.2.0.dist-info/LICENSE
rtreelib-0.2.0.dist-info/METADATA
rtreelib-0.2.0.dist-info/WHEEL
rtreelib-0.2.0.dist-info/top_level.txt
rtreelib-0.2.0.dist-info/RECORD
