Metadata-Version: 2.1
Name: rtreelib
Version: 0.2.0
Summary: Pluggable R-tree implementation in pure Python.
Home-page: http://github.com/sergkr/rtreelib
Author: Sergey Krilov
License: MIT
Platform: UNKNOWN
Classifier: License :: OSI Approved :: MIT License
Classifier: Programming Language :: Python
Classifier: Programming Language :: Python :: 3
Classifier: Programming Language :: Python :: 3.6
Classifier: Programming Language :: Python :: Implementation :: CPython
Classifier: Programming Language :: Python :: Implementation :: PyPy
Requires-Python: >=3.6.0
Provides-Extra: diagram
Requires-Dist: matplotlib (>=3.0.0) ; extra == 'diagram'
Requires-Dist: pydot (>=1.3.0) ; extra == 'diagram'
Requires-Dist: tqdm (>=v4.31.0) ; extra == 'diagram'
